dumbvector/FOR DELETE dumb_vector_s3.py
dumbvector/__init__.py
dumbvector/bsonutil.py
dumbvector/docs.py
dumbvector/docs_s3.py
dumbvector/dumb_index.py
dumbvector/dumb_index_s3.py
dumbvector/numtypes.py
dumbvector/search.py
dumbvector/util.py
dumbvector-0.1.0.dist-info/LICENSE
dumbvector-0.1.0.dist-info/METADATA
dumbvector-0.1.0.dist-info/WHEEL
dumbvector-0.1.0.dist-info/top_level.txt
dumbvector-0.1.0.dist-info/RECORD
