Metadata-Version: 2.1
Name: dumbvector
Version: 0.1.0
Summary: Semantic Search done the dumb way.
Home-page: https://github.com/emlynoregan/dumbvector
Author: Emlyn O'Regan
Author-email: emlynoregan@gmail.com
License: Apache License 2.0
Classifier: Development Status :: 3 - Alpha
Classifier: License :: OSI Approved :: Apache Software License
Classifier: Programming Language :: Python :: 3
Classifier: Programming Language :: Python :: 3.6
Classifier: Programming Language :: Python :: 3.7
Classifier: Programming Language :: Python :: 3.8
Classifier: Programming Language :: Python :: 3.9
Classifier: Programming Language :: Python :: 3.10
Classifier: Programming Language :: Python :: 3.11
License-File: LICENSE
Requires-Dist: numpy
Requires-Dist: bson
